django_cte/__init__.py
django_cte/_deprecated.py
django_cte/cte.py
django_cte/jitmixin.py
django_cte/join.py
django_cte/meta.py
django_cte/query.py
django_cte/raw.py
django_cte-2.0.0.dist-info/licenses/LICENSE
django_cte-2.0.0.dist-info/WHEEL
django_cte-2.0.0.dist-info/METADATA
django_cte-2.0.0.dist-info/RECORD
