Metadata-Version: 2.4
Name: django-cte
Version: 2.0.0
Summary: Common Table Expressions (CTE) for Django
Author-email: Daniel Miller <millerdev@gmail.com>
Requires-Python: >= 3.9
Classifier: Development Status :: 5 - Production/Stable
Classifier: Environment :: Web Environment
Classifier: Framework :: Django
Classifier: Intended Audience :: Developers
Classifier: License :: OSI Approved :: BSD License
Classifier: Operating System :: OS Independent
Classifier: Programming Language :: Python
Classifier: Programming Language :: Python :: 3
Classifier: Programming Language :: Python :: 3.9
Classifier: Programming Language :: Python :: 3.10
Classifier: Programming Language :: Python :: 3.11
Classifier: Programming Language :: Python :: 3.12
Classifier: Programming Language :: Python :: 3.13
Classifier: Programming Language :: Python :: 3.14
Classifier: Framework :: Django
Classifier: Framework :: Django :: 4
Classifier: Framework :: Django :: 4.2
Classifier: Framework :: Django :: 5
Classifier: Framework :: Django :: 5.1
Classifier: Framework :: Django :: 5.2
Classifier: Topic :: Software Development :: Libraries :: Python Modules
License-File: LICENSE
Requires-Dist: django
Project-URL: Home, https://github.com/dimagi/django-cte
